Qube2-0.3.43.data/scripts/booster
qube/__init__.py
qube/qube_nb_magic_init.py
qube/booster/__init__.py
qube/booster/boosterai.py
qube/booster/core.py
qube/booster/simctrl.py
qube/booster/utils.py
qube/booster/app/__init__.py
qube/booster/app/boo.py
qube/booster/app/reports.py
qube/booster/app/signal_viewer.py
qube/booster/app/templates/detailed_report.html
qube/booster/app/templates/experiment_chart_report.html
qube/booster/app/templates/experiment_report.html
qube/booster/app/templates/experiments_index.html
qube/booster/app/templates/index.html
qube/booster/app/templates/main_report.html
qube/booster/app/templates/signals_viewer.html
qube/booster/app/templates/tearsheet_report.html
qube/booster/data/markets.yml
qube/charting/__init__.py
qube/charting/lookinglass.py
qube/charting/mpl_finance.py
qube/charting/plot_helpers.py
qube/charting/highcharts/__init__.py
qube/charting/highcharts/core.py
qube/charting/highcharts/display.py
qube/configs/Properties.py
qube/configs/__init__.py
qube/configs/config-default/datasource.json
qube/configs/config-default/dukas_outlook.csv
qube/configs/config-default/main-props.json
qube/configs/config-test/datasource.json
qube/configs/config-test/dukas_outlook.csv
qube/configs/config-test/main-props.json
qube/datasource/CsvConnector.py
qube/datasource/DataSource.py
qube/datasource/DataserverConnector.py
qube/datasource/DukasOutlookConnector.py
qube/datasource/InMemoryDataSource.py
qube/datasource/KdbConnector.py
qube/datasource/MongoConnector.py
qube/datasource/YahooConnector.py
qube/datasource/__init__.py
qube/datasource/loaders.py
qube/datasource/controllers/KdbServerController.py
qube/datasource/controllers/MemcacheController.py
qube/datasource/controllers/MongoController.py
qube/datasource/controllers/__init__.py
qube/datasource/controllers/kdb_utils.py
qube/examples/__init__.py
qube/examples/booster/test_portfolio_task.yml
qube/examples/learn/__init__.py
qube/examples/learn/filters.py
qube/examples/learn/generators.py
Qube2-0.3.43.dist-info/LICENSE
Qube2-0.3.43.dist-info/METADATA
Qube2-0.3.43.dist-info/WHEEL
Qube2-0.3.43.dist-info/top_level.txt
Qube2-0.3.43.dist-info/RECORD
